jars/__init__.py
jars/iceberg-aws-bundle-1.7.0.jar.py
jars/iceberg-spark-runtime-3.5_2.12-1.7.0.jar.py
phoenix/__init__.py
phoenix/main.py
cphoenix-1.0.3.dist-info/METADATA
cphoenix-1.0.3.dist-info/WHEEL
cphoenix-1.0.3.dist-info/top_level.txt
cphoenix-1.0.3.dist-info/RECORD
